Metadata-Version: 2.1
Name: pyseneye-windows
Version: 0.0.2
Summary: A module for interacting with the Seneye range or aquarium and pond sensors
Home-page: http://github.com/iamthecage/pyseneye_windows/
Author: Stephen Mc Gowan
Author-email: mcclown@gmail.com
License: Apache Software License
Platform: any
Classifier: Programming Language :: Python
Classifier: Development Status :: 3 - Alpha
Classifier: Natural Language :: English
Classifier: Environment :: Web Environment
Classifier: Intended Audience :: Developers
Classifier: License :: OSI Approved :: Apache Software License
Classifier: Operating System :: OS Independent
Classifier: Topic :: Software Development :: Libraries :: Python Modules
Classifier: Topic :: Home Automation
Classifier: Topic :: System :: Hardware
Provides-Extra: testing
